arangodb_pythongraph/__init__.py
arangodb_pythongraph/aql_pythongraph.py
arangodb_pythongraph-0.1.4.dist-info/LICENSE
arangodb_pythongraph-0.1.4.dist-info/WHEEL
arangodb_pythongraph-0.1.4.dist-info/METADATA
arangodb_pythongraph-0.1.4.dist-info/RECORD
